indexed_gzip/zran_file_util.pxd
indexed_gzip/zran.pxd
indexed_gzip/zran_file_util.c
indexed_gzip/__init__.py
indexed_gzip/zran.h
indexed_gzip/set_traceback.pxd
indexed_gzip/indexed_gzip.pyx
indexed_gzip/zran_file_util.h
indexed_gzip/indexed_gzip.cpython-310-darwin.so
indexed_gzip/indexed_gzip.c
indexed_gzip/zran.c
indexed_gzip/tests/benchmark_bandwidth.py
indexed_gzip/tests/conftest.py
indexed_gzip/tests/test_nibabel_integration.py
indexed_gzip/tests/benchmark.py
indexed_gzip/tests/__init__.py
indexed_gzip/tests/test_indexed_gzip_threading.py
indexed_gzip/tests/ctest_zran.pyx
indexed_gzip/tests/test_zran.py
indexed_gzip/tests/test_indexed_gzip.py
indexed_gzip/tests/__main__.py
indexed_gzip-1.10.3.dist-info/RECORD
indexed_gzip-1.10.3.dist-info/WHEEL
indexed_gzip-1.10.3.dist-info/top_level.txt
indexed_gzip-1.10.3.dist-info/METADATA
indexed_gzip-1.10.3.dist-info/licenses/LICENSE
