Metadata-Version: 2.1
Name: indexed_gzip
Version: 1.10.3
Summary: Fast random access of gzip files in Python
Maintainer-email: Paul McCarthy <pauldmccarthy@gmail.com>
License: Zlib
Project-URL: Repository, https://github.com/pauldmccarthy/indexed_gzip
Classifier: Development Status :: 3 - Alpha
Classifier: Intended Audience :: Developers
Classifier: Programming Language :: C
Classifier: Programming Language :: Cython
Classifier: Programming Language :: Python :: 2
Classifier: Programming Language :: Python :: 3
Classifier: Topic :: System :: Archiving :: Compression
Requires-Python: >=3.7
License-File: LICENSE
Provides-Extra: test
Requires-Dist: pytest ; extra == 'test'
Requires-Dist: numpy ; extra == 'test'
Requires-Dist: nibabel ; extra == 'test'
Requires-Dist: coverage ; extra == 'test'
Requires-Dist: pytest-cov ; extra == 'test'
